ndx_acquisition_module/VERSION
ndx_acquisition_module/__init__.py
ndx_acquisition_module/spec/ndx-acquisition-module.extensions.yaml
ndx_acquisition_module/spec/ndx-acquisition-module.namespace.yaml
ndx_acquisition_module-0.1.2.dist-info/LICENSE.txt
ndx_acquisition_module-0.1.2.dist-info/METADATA
ndx_acquisition_module-0.1.2.dist-info/WHEEL
ndx_acquisition_module-0.1.2.dist-info/top_level.txt
ndx_acquisition_module-0.1.2.dist-info/RECORD
