Metadata-Version: 2.1
Name: ndx-acquisition-module
Version: 0.1.2
Summary: NWB extension to add acquisition module
Author-email: Tuan Pham <tuanhpham@brown.edu>
Maintainer-email: Tuan Pham <tuanhpham@brown.edu>
License: BSD-3
Project-URL: Repository, https://gitlab.com/fleischmann-lab/ndx/ndx-acquisition-module
Project-URL: Homepage, https://gitlab.com/fleischmann-lab/ndx/ndx-acquisition-module
Project-URL: Bug Tracker, https://gitlab.com/fleischmann-lab/ndx/ndx-acquisition-module/issues
Project-URL: Documentation, https://fleischmann-lab.gitlab.io/ndx/ndx-acquisition-module
Keywords: NeurodataWithoutBorders,NWB,nwb-extension,ndx-extension
Classifier: Development Status :: 3 - Alpha
Classifier: Intended Audience :: Developers
Classifier: Intended Audience :: Science/Research
Classifier: License :: OSI Approved :: BSD License
Classifier: Programming Language :: Python :: 3.8
Classifier: Programming Language :: Python :: 3.9
Classifier: Programming Language :: Python :: 3.10
Classifier: Programming Language :: Python :: 3.11
Requires-Python: >=3.8
License-File: LICENSE.txt
Requires-Dist: pynwb (<3,>=1.5.0)
Requires-Dist: hdmf (<4,>=3.4.7)
Provides-Extra: dev
Requires-Dist: black (>=22.0) ; extra == 'dev'
Requires-Dist: flake8 (>=6.0) ; extra == 'dev'
Requires-Dist: pytest (>=7.0) ; extra == 'dev'
Requires-Dist: isort (>=5.11) ; extra == 'dev'
Requires-Dist: pytest-subtests (==0.6.0) ; extra == 'dev'
Requires-Dist: hdmf-docutils (==0.4.4) ; extra == 'dev'
Requires-Dist: codespell (>=2.2) ; extra == 'dev'
Requires-Dist: hypothesis ; extra == 'dev'
Requires-Dist: ipython ; extra == 'dev'
Requires-Dist: furo ; extra == 'dev'
